{
    "key": "group_59df074207496",
    "title": "Project (Post Type)",
    "fields": [
        {
            "key": "field_59df07472580d",
            "label": "Project Content Type",
            "name": "project_content_type",
            "type": "radio",
            "instructions": "",
            "required": 0,
            "conditional_logic": 0,
            "wrapper": {
                "width": "",
                "class": "",
                "id": ""
            },
            "choices": {
                "text": "Plain Content (Rich Text Editor)",
                "artist_list": "Artwork and Artists List",
                "artist_single": "Artwork and Artists Single",
                "program_list": "Public Programs List",
                "program_single": "Public Programs Single",
                "collapsable_sections": "Collapsable Sections (FAQ)",
                "events": "Events",
                "media": "Media",
                "podcast": "Podcast"
            },
            "allow_null": 0,
            "other_choice": 0,
            "save_other_choice": 0,
            "default_value": "",
            "layout": "vertical",
            "return_format": "value"
        },
        {
            "key": "field_5a2b66d05f6b7",
            "label": "<h1 style=\"color: red;\">Detail Page Reminder<\/h1>",
            "name": "",
            "type": "message",
            "instructions": "",
            "required": 0,
            "conditional_logic": [
                [
                    {
                        "field": "field_59df07472580d",
                        "operator": "==",
                        "value": "artist_single"
                    }
                ]
            ],
            "wrapper": {
                "width": "",
                "class": "",
                "id": ""
            },
            "message": "Remember to set the parent to this page in order for the \"BACK: ...\" link at the bottom of the page to work. The parent page should be <b>the project's<\/b> relevant page--e.g. Artwork and Artists, Public Programs.",
            "new_lines": "wpautop",
            "esc_html": 0
        },
        {
            "key": "field_5a13227addc7a",
            "label": "Project Subtitle",
            "name": "project_subtitle",
            "type": "text",
            "instructions": "",
            "required": 0,
            "conditional_logic": [
                [
                    {
                        "field": "field_59df07472580d",
                        "operator": "==",
                        "value": "artist_single"
                    }
                ]
            ],
            "wrapper": {
                "width": "",
                "class": "",
                "id": ""
            },
            "default_value": "",
            "placeholder": "",
            "prepend": "",
            "append": "",
            "maxlength": ""
        },
        {
            "key": "field_59e574cd18ce1",
            "label": "Project Image Slider",
            "name": "project_image_slider",
            "type": "gallery",
            "instructions": "To add the slider anywhere into the content area, add the shortcode \"slider\" like this:<br>[slider]",
            "required": 0,
            "conditional_logic": [
                [
                    {
                        "field": "field_59df07472580d",
                        "operator": "==",
                        "value": "artist_single"
                    }
                ],
                [
                    {
                        "field": "field_59df07472580d",
                        "operator": "==",
                        "value": "program_single"
                    }
                ],
                [
                    {
                        "field": "field_59df07472580d",
                        "operator": "==",
                        "value": "text"
                    }
                ]
            ],
            "wrapper": {
                "width": "",
                "class": "",
                "id": ""
            },
            "min": "",
            "max": "",
            "insert": "append",
            "library": "all",
            "min_width": "",
            "min_height": "",
            "min_size": "",
            "max_width": "",
            "max_height": "",
            "max_size": "",
            "mime_types": ""
        },
        {
            "key": "field_5a2b57be3483e",
            "label": "Related Content",
            "name": "related_content",
            "type": "repeater",
            "instructions": "",
            "required": 0,
            "conditional_logic": [
                [
                    {
                        "field": "field_59df07472580d",
                        "operator": "==",
                        "value": "artist_single"
                    }
                ]
            ],
            "wrapper": {
                "width": "",
                "class": "",
                "id": ""
            },
            "collapsed": "",
            "min": 0,
            "max": 3,
            "layout": "block",
            "button_label": "Add Related Item",
            "sub_fields": [
                {
                    "key": "field_5a2b58207c1db",
                    "label": "Item URL",
                    "name": "item_url",
                    "type": "link",
                    "instructions": "",
                    "required": 0,
                    "conditional_logic": 0,
                    "wrapper": {
                        "width": "",
                        "class": "",
                        "id": ""
                    },
                    "return_format": "array"
                },
                {
                    "key": "field_5a2b58a37c1dc",
                    "label": "Item Title",
                    "name": "item_title",
                    "type": "text",
                    "instructions": "",
                    "required": 0,
                    "conditional_logic": 0,
                    "wrapper": {
                        "width": "",
                        "class": "",
                        "id": ""
                    },
                    "default_value": "",
                    "placeholder": "",
                    "prepend": "",
                    "append": "",
                    "maxlength": ""
                },
                {
                    "key": "field_5a2b58b87c1dd",
                    "label": "Item Description",
                    "name": "item_description",
                    "type": "textarea",
                    "instructions": "",
                    "required": 0,
                    "conditional_logic": 0,
                    "wrapper": {
                        "width": "",
                        "class": "",
                        "id": ""
                    },
                    "default_value": "",
                    "placeholder": "",
                    "maxlength": "",
                    "rows": "",
                    "new_lines": ""
                },
                {
                    "key": "field_5a2b5c8e7c1de",
                    "label": "Item Type",
                    "name": "item_type",
                    "type": "text",
                    "instructions": "",
                    "required": 0,
                    "conditional_logic": 0,
                    "wrapper": {
                        "width": "",
                        "class": "",
                        "id": ""
                    },
                    "default_value": "",
                    "placeholder": "",
                    "prepend": "",
                    "append": "",
                    "maxlength": ""
                },
                {
                    "key": "field_5a2b5c967c1df",
                    "label": "Item Call to Action",
                    "name": "item_call_to_action",
                    "type": "text",
                    "instructions": "",
                    "required": 0,
                    "conditional_logic": 0,
                    "wrapper": {
                        "width": "",
                        "class": "",
                        "id": ""
                    },
                    "default_value": "",
                    "placeholder": "",
                    "prepend": "",
                    "append": "",
                    "maxlength": ""
                },
                {
                    "key": "field_5a2b5c9e7c1e0",
                    "label": "Item Image",
                    "name": "item_image",
                    "type": "image",
                    "instructions": "",
                    "required": 0,
                    "conditional_logic": 0,
                    "wrapper": {
                        "width": "",
                        "class": "",
                        "id": ""
                    },
                    "return_format": "array",
                    "preview_size": "thumbnail",
                    "library": "all",
                    "min_width": "",
                    "min_height": "",
                    "min_size": "",
                    "max_width": "",
                    "max_height": "",
                    "max_size": "",
                    "mime_types": ""
                }
            ]
        },
        {
            "key": "field_59df0a92401d0",
            "label": "Project Grid Content",
            "name": "project_grid_content",
            "type": "repeater",
            "instructions": "",
            "required": 0,
            "conditional_logic": [
                [
                    {
                        "field": "field_59df07472580d",
                        "operator": "==",
                        "value": "artist_list"
                    }
                ],
                [
                    {
                        "field": "field_59df07472580d",
                        "operator": "==",
                        "value": "program_list"
                    }
                ]
            ],
            "wrapper": {
                "width": "",
                "class": "",
                "id": ""
            },
            "collapsed": "",
            "min": 0,
            "max": 0,
            "layout": "block",
            "button_label": "Add Item",
            "sub_fields": [
                {
                    "key": "field_5a131e3b3a44a",
                    "label": "Grid Content",
                    "name": "grid_content",
                    "type": "post_object",
                    "instructions": "",
                    "required": 0,
                    "conditional_logic": 0,
                    "wrapper": {
                        "width": "",
                        "class": "",
                        "id": ""
                    },
                    "post_type": [
                        "project"
                    ],
                    "taxonomy": [],
                    "allow_null": 0,
                    "multiple": 0,
                    "return_format": "object",
                    "ui": 1
                }
            ]
        },
        {
            "key": "field_5a2e1b85929b2",
            "label": "Upcoming Programs Section Title",
            "name": "upcoming_programs_section_title",
            "type": "text",
            "instructions": "",
            "required": 0,
            "conditional_logic": [
                [
                    {
                        "field": "field_59df07472580d",
                        "operator": "==",
                        "value": "program_single"
                    }
                ]
            ],
            "wrapper": {
                "width": "",
                "class": "",
                "id": ""
            },
            "default_value": "",
            "placeholder": "",
            "prepend": "",
            "append": "",
            "maxlength": ""
        },
        {
            "key": "field_5a2dbb205b631",
            "label": "Upcoming Programs",
            "name": "upcoming_programs",
            "type": "repeater",
            "instructions": "",
            "required": 0,
            "conditional_logic": [
                [
                    {
                        "field": "field_59df07472580d",
                        "operator": "==",
                        "value": "program_single"
                    }
                ]
            ],
            "wrapper": {
                "width": "",
                "class": "",
                "id": ""
            },
            "collapsed": "",
            "min": 0,
            "max": 0,
            "layout": "table",
            "button_label": "",
            "sub_fields": [
                {
                    "key": "field_5a2dbb505b632",
                    "label": "Event",
                    "name": "event",
                    "type": "post_object",
                    "instructions": "",
                    "required": 0,
                    "conditional_logic": 0,
                    "wrapper": {
                        "width": "",
                        "class": "",
                        "id": ""
                    },
                    "post_type": [
                        "tribe_events"
                    ],
                    "taxonomy": [],
                    "allow_null": 0,
                    "multiple": 0,
                    "return_format": "object",
                    "ui": 1
                }
            ]
        },
        {
            "key": "field_5a2e1f34cb7d5",
            "label": "Collapsable Sections",
            "name": "collapsable_sections",
            "type": "repeater",
            "instructions": "",
            "required": 0,
            "conditional_logic": [
                [
                    {
                        "field": "field_59df07472580d",
                        "operator": "==",
                        "value": "collapsable_sections"
                    }
                ]
            ],
            "wrapper": {
                "width": "",
                "class": "",
                "id": ""
            },
            "collapsed": "",
            "min": 0,
            "max": 0,
            "layout": "block",
            "button_label": "Add Section",
            "sub_fields": [
                {
                    "key": "field_5a2e1f52cb7d6",
                    "label": "Section Title",
                    "name": "section_title",
                    "type": "text",
                    "instructions": "",
                    "required": 0,
                    "conditional_logic": 0,
                    "wrapper": {
                        "width": "",
                        "class": "",
                        "id": ""
                    },
                    "default_value": "",
                    "placeholder": "",
                    "prepend": "",
                    "append": "",
                    "maxlength": ""
                },
                {
                    "key": "field_5a2e1f58cb7d7",
                    "label": "Section Content",
                    "name": "section_content",
                    "type": "wysiwyg",
                    "instructions": "",
                    "required": 0,
                    "conditional_logic": 0,
                    "wrapper": {
                        "width": "",
                        "class": "",
                        "id": ""
                    },
                    "default_value": "",
                    "tabs": "all",
                    "toolbar": "full",
                    "media_upload": 1,
                    "delay": 0
                }
            ]
        },
        {
            "key": "field_5a35af2107f12",
            "label": "Media Files",
            "name": "media_files",
            "type": "repeater",
            "instructions": "",
            "required": 0,
            "conditional_logic": [
                [
                    {
                        "field": "field_59df07472580d",
                        "operator": "==",
                        "value": "media"
                    }
                ]
            ],
            "wrapper": {
                "width": "",
                "class": "",
                "id": ""
            },
            "collapsed": "",
            "min": 0,
            "max": 0,
            "layout": "block",
            "button_label": "Add Media File",
            "sub_fields": [
                {
                    "key": "field_5a35b02507f13",
                    "label": "Media File Title",
                    "name": "media_file_title",
                    "type": "text",
                    "instructions": "",
                    "required": 0,
                    "conditional_logic": 0,
                    "wrapper": {
                        "width": "",
                        "class": "",
                        "id": ""
                    },
                    "default_value": "",
                    "placeholder": "",
                    "prepend": "",
                    "append": "",
                    "maxlength": ""
                },
                {
                    "key": "field_5a35b05007f14",
                    "label": "Media File Date",
                    "name": "media_file_date",
                    "type": "date_picker",
                    "instructions": "",
                    "required": 0,
                    "conditional_logic": 0,
                    "wrapper": {
                        "width": "",
                        "class": "",
                        "id": ""
                    },
                    "display_format": "F j, Y",
                    "return_format": "F j, Y",
                    "first_day": 1
                },
                {
                    "key": "field_5a3726881de03",
                    "label": "Media Video Embed",
                    "name": "media_video_embed",
                    "type": "textarea",
                    "instructions": "",
                    "required": 0,
                    "conditional_logic": 0,
                    "wrapper": {
                        "width": "",
                        "class": "",
                        "id": ""
                    },
                    "default_value": "",
                    "placeholder": "<iframe src=\"https:\/\/www.facebook.com\/plugins\/video.php?href=https%3A%2F%2Fwww.facebook.com%2FBetweenTheScenes%2Fvideos%2F118476265518814%2F&show_text=0&width=560\" width=\"560\" height=\"315\" style=\"border:none;overflow:hidden\" scrolling=\"no\" frameborder=\"0\" allowTransparency=\"true\" allowFullScreen=\"true\"><\/iframe>",
                    "maxlength": "",
                    "rows": 4,
                    "new_lines": ""
                },
                {
                    "key": "field_5a389b4196d8b",
                    "label": "Media Audio Embed",
                    "name": "media_audio_embed",
                    "type": "textarea",
                    "instructions": "",
                    "required": 0,
                    "conditional_logic": 0,
                    "wrapper": {
                        "width": "",
                        "class": "",
                        "id": ""
                    },
                    "default_value": "",
                    "placeholder": "<iframe width=\"100%\" height=\"166\" scrolling=\"no\" frameborder=\"no\" src=\"https:\/\/w.soundcloud.com\/player\/?url=https%3A\/\/api.soundcloud.com\/tracks\/260295175&amp;color=%23ff5500&amp;auto_play=false&amp;hide_related=false&amp;show_comments=true&amp;show_user=true&amp;show_reposts=false&amp;show_teaser=true\"><\/iframe>",
                    "maxlength": "",
                    "rows": 4,
                    "new_lines": ""
                }
            ]
        },
        {
            "key": "field_5a38a6d5e271c",
            "label": "Podcast Cover Image",
            "name": "podcast_cover_image",
            "type": "image",
            "instructions": "",
            "required": 0,
            "conditional_logic": [
                [
                    {
                        "field": "field_59df07472580d",
                        "operator": "==",
                        "value": "podcast"
                    }
                ]
            ],
            "wrapper": {
                "width": "",
                "class": "",
                "id": ""
            },
            "return_format": "array",
            "preview_size": "thumbnail",
            "library": "all",
            "min_width": "",
            "min_height": "",
            "min_size": "",
            "max_width": "",
            "max_height": "",
            "max_size": "",
            "mime_types": ""
        },
        {
            "key": "field_5a38a6e7e271d",
            "label": "Podcast Intro Text",
            "name": "podcast_intro_text",
            "type": "wysiwyg",
            "instructions": "",
            "required": 0,
            "conditional_logic": [
                [
                    {
                        "field": "field_59df07472580d",
                        "operator": "==",
                        "value": "podcast"
                    }
                ]
            ],
            "wrapper": {
                "width": "",
                "class": "",
                "id": ""
            },
            "default_value": "",
            "tabs": "all",
            "toolbar": "full",
            "media_upload": 1,
            "delay": 0
        },
        {
            "key": "field_5a38a77bc9185",
            "label": "Podcast Episodes",
            "name": "podcast_episodes",
            "type": "repeater",
            "instructions": "",
            "required": 0,
            "conditional_logic": [
                [
                    {
                        "field": "field_59df07472580d",
                        "operator": "==",
                        "value": "podcast"
                    }
                ]
            ],
            "wrapper": {
                "width": "",
                "class": "",
                "id": ""
            },
            "collapsed": "",
            "min": 0,
            "max": 0,
            "layout": "block",
            "button_label": "Add Podcast Episode",
            "sub_fields": [
                {
                    "key": "field_5a38a7c0c9186",
                    "label": "Podcast Episode",
                    "name": "podcast_episode",
                    "type": "text",
                    "instructions": "",
                    "required": 0,
                    "conditional_logic": 0,
                    "wrapper": {
                        "width": "",
                        "class": "",
                        "id": ""
                    },
                    "default_value": "",
                    "placeholder": "Episode 7",
                    "prepend": "",
                    "append": "",
                    "maxlength": ""
                },
                {
                    "key": "field_5a38a7d4c9187",
                    "label": "Podcast Episode Title",
                    "name": "podcast_episode_title",
                    "type": "text",
                    "instructions": "",
                    "required": 0,
                    "conditional_logic": 0,
                    "wrapper": {
                        "width": "",
                        "class": "",
                        "id": ""
                    },
                    "default_value": "",
                    "placeholder": "",
                    "prepend": "",
                    "append": "",
                    "maxlength": ""
                },
                {
                    "key": "field_5a38a7e5c9188",
                    "label": "Podcast Episode Date",
                    "name": "podcast_episode_date",
                    "type": "date_picker",
                    "instructions": "",
                    "required": 0,
                    "conditional_logic": 0,
                    "wrapper": {
                        "width": "",
                        "class": "",
                        "id": ""
                    },
                    "display_format": "F j, Y",
                    "return_format": "F j, Y",
                    "first_day": 1
                },
                {
                    "key": "field_5a38a800c9189",
                    "label": "Podcast Episode Length",
                    "name": "podcast_episode_length",
                    "type": "text",
                    "instructions": "",
                    "required": 0,
                    "conditional_logic": 0,
                    "wrapper": {
                        "width": "",
                        "class": "",
                        "id": ""
                    },
                    "default_value": "",
                    "placeholder": "51 Minutes",
                    "prepend": "",
                    "append": "",
                    "maxlength": ""
                },
                {
                    "key": "field_5a38a81dc918a",
                    "label": "Podcast Episode Description",
                    "name": "podcast_episode_description",
                    "type": "textarea",
                    "instructions": "",
                    "required": 0,
                    "conditional_logic": 0,
                    "wrapper": {
                        "width": "",
                        "class": "",
                        "id": ""
                    },
                    "default_value": "",
                    "placeholder": "",
                    "maxlength": "",
                    "rows": 4,
                    "new_lines": ""
                },
                {
                    "key": "field_5a38a833c918b",
                    "label": "Podcast Episode Embed",
                    "name": "podcast_episode_embed",
                    "type": "textarea",
                    "instructions": "",
                    "required": 0,
                    "conditional_logic": 0,
                    "wrapper": {
                        "width": "",
                        "class": "",
                        "id": ""
                    },
                    "default_value": "",
                    "placeholder": "",
                    "maxlength": "",
                    "rows": 4,
                    "new_lines": ""
                }
            ]
        }
    ],
    "location": [
        [
            {
                "param": "post_type",
                "operator": "==",
                "value": "project"
            }
        ]
    ],
    "menu_order": 1,
    "position": "acf_after_title",
    "style": "default",
    "label_placement": "top",
    "instruction_placement": "label",
    "hide_on_screen": [
        "revisions",
        "author"
    ],
    "active": 1,
    "description": "",
    "modified": 1513698121
}